examples/__init__.py
examples/classification_conftr_cifar100.py
examples/classification_confts_cifar100.py
examples/classification_splitcp_cifar100.py
examples/classification_splitcp_cifar100_online.py
examples/classification_ua_trainer_cifar10.py
examples/gnn_inductive_computers.py
examples/gnn_trainer_coraml.py
examples/gnn_transductive_coraml.py
examples/llm_ConformalLM_TriviaQA.py
examples/llm_utils.py
examples/regression_cqr_synthetic.py
examples/regression_split_norabs.py
examples/regression_split_synthetic_cpd.py
examples/regression_split_synthetic_online.py
examples/timeseries_aci_synthetic.py
examples/utils.py
tests/__init__.py
tests/classification/__init__.py
tests/classification/loss/__init__.py
tests/classification/loss/test_cd.py
tests/classification/loss/test_conftr.py
tests/classification/loss/test_confts.py
tests/classification/loss/test_loss_base.py
tests/classification/loss/test_scpo.py
tests/classification/loss/test_uncertainty_aware.py
tests/classification/predictor/__init__.py
tests/classification/predictor/test_classwise.py
tests/classification/predictor/test_cluster.py
tests/classification/predictor/test_cpds_predictor.py
tests/classification/predictor/test_predictor_base.py
tests/classification/predictor/test_rc3p.py
tests/classification/predictor/test_split.py
tests/classification/predictor/test_utils.py
tests/classification/predictor/test_weight.py
tests/classification/score/__init__.py
tests/classification/score/test_aps.py
tests/classification/score/test_entmax.py
tests/classification/score/test_knn.py
tests/classification/score/test_lac.py
tests/classification/score/test_margin.py
tests/classification/score/test_raps.py
tests/classification/score/test_saps.py
tests/classification/score/test_score_base.py
tests/classification/score/test_topk.py
tests/classification/trainer/__init__.py
tests/classification/trainer/test_base_trainer.py
tests/classification/trainer/test_conftr_trainer.py
tests/classification/trainer/test_confts_trainer.py
torchcp-1.2.1.dist-info/licenses/AUTHORS.txt
torchcp-1.2.1.dist-info/licenses/LICENSE
torchcp-1.2.1.dist-info/licenses/LICENSE.GPL
torchcp-1.2.1.dist-info/METADATA
torchcp-1.2.1.dist-info/WHEEL
torchcp-1.2.1.dist-info/top_level.txt
torchcp-1.2.1.dist-info/RECORD
