Metadata-Version: 2.4
Name: torchcp
Version: 1.2.1
Summary: A Python toolbox for conformal prediction on deep learning models.
Home-page: https://github.com/ml-stat-Sustech/TorchCP
License-File: LICENSE
License-File: LICENSE.GPL
License-File: AUTHORS.txt
Requires-Dist: torch>=2.1.0
Requires-Dist: torchvision>=0.16.0
Requires-Dist: transformers>=4.20.0
Requires-Dist: numpy>=1.20.0
Requires-Dist: setuptools>=59.5.0
Requires-Dist: tqdm>=4.60.0
Requires-Dist: scikit-learn>=1.5.0
Requires-Dist: pandas>=2.1.4
Requires-Dist: Pillow>=10.3.0
Requires-Dist: torch_geometric>=2.4.0
Requires-Dist: torchsort>=0.1.9
Dynamic: description
Dynamic: description-content-type
Dynamic: home-page
Dynamic: license-file
Dynamic: requires-dist
Dynamic: summary
